arcfutil/cv/__init__.py
arcfutil_cvkit-0.0.2.dist-info/LICENSE
arcfutil_cvkit-0.0.2.dist-info/METADATA
arcfutil_cvkit-0.0.2.dist-info/WHEEL
arcfutil_cvkit-0.0.2.dist-info/top_level.txt
arcfutil_cvkit-0.0.2.dist-info/RECORD
