Metadata-Version: 2.1
Name: arcfutil-cvkit
Version: 0.0.2
Summary: OpenCV related plugin for arcfutil
Home-page: https://github.com/feightwywx/arcfutil-cvkit
Author: .direwolf
Author-email: kururinmiracle@outlook.com
License: UNKNOWN
Platform: UNKNOWN
Classifier: Programming Language :: Python :: 3
Classifier: Environment :: Plugins
Classifier: Intended Audience :: Developers
Classifier: License :: OSI Approved :: MIT License
Classifier: Operating System :: OS Independent
Classifier: Topic :: Multimedia :: Graphics :: Graphics Conversion
Requires-Python: >=3.8
Requires-Dist: arcfutil (>=0.7.0)
Requires-Dist: numpy (==1.22.1)
Requires-Dist: opencv-python (==4.5.5.62)
